{
  "counts": [
    {
      "x": "2019-07-02T03:52:34-04:00",
      "y": 0
    },
    {
      "x": "2019-07-02T04:07:34-04:00",
      "y": 0
    },
    {
      "x": "2019-07-02T04:22:34-04:00",
      "y": 0
    },
    {
      "x": "2019-07-02T04:37:34-04:00",
      "y": 0
    },
    {
      "x": "2019-07-02T04:52:34-04:00",
      "y": 0
    },
    {
      "x": "2019-07-02T05:07:34-04:00",
      "y": 0
    },
    {
      "x": "2019-07-02T05:22:34-04:00",
      "y": 0
    },
    {
      "x": "2019-07-02T05:37:34-04:00",
      "y": 0
    },
    {
      "x": "2019-07-02T05:52:34-04:00",
      "y": 0
    },
    {
      "x": "2019-07-02T06:07:34-04:00",
      "y": 1
    },
    {
      "x": "2019-07-02T06:22:34-04:00",
      "y": 0
    },
    {
      "x": "2019-07-02T06:37:34-04:00",
      "y": 0
    },
    {
      "x": "2019-07-02T06:52:34-04:00",
      "y": 0
    },
    {
      "x": "2019-07-02T07:07:34-04:00",
      "y": 0
    },
    {
      "x": "2019-07-02T07:22:34-04:00",
      "y": 0
    },
    {
      "x": "2019-07-02T07:37:34-04:00",
      "y": 0
    },
    {
      "x": "2019-07-02T07:52:34-04:00",
      "y": 0
    },
    {
      "x": "2019-07-02T08:07:34-04:00",
      "y": 0
    },
    {
      "x": "2019-07-02T08:22:34-04:00",
      "y": 2
    },
    {
      "x": "2019-07-02T08:37:34-04:00",
      "y": 0
    },
    {
      "x": "2019-07-02T08:52:34-04:00",
      "y": 0
    },
    {
      "x": "2019-07-02T09:07:34-04:00",
      "y": 1
    },
    {
      "x": "2019-07-02T09:22:34-04:00",
      "y": 1
    },
    {
      "x": "2019-07-02T09:37:34-04:00",
      "y": 1
    },
    {
      "x": "2019-07-02T09:52:34-04:00",
      "y": 1
    },
    {
      "x": "2019-07-02T10:07:34-04:00",
      "y": 3
    },
    {
      "x": "2019-07-02T10:22:34-04:00",
      "y": 7
    },
    {
      "x": "2019-07-02T10:37:34-04:00",
      "y": 5
    },
    {
      "x": "2019-07-02T10:52:34-04:00",
      "y": 6
    },
    {
      "x": "2019-07-02T11:07:34-04:00",
      "y": 6
    },
    {
      "x": "2019-07-02T11:22:34-04:00",
      "y": 4
    },
    {
      "x": "2019-07-02T11:37:34-04:00",
      "y": 4
    },
    {
      "x": "2019-07-02T11:52:34-04:00",
      "y": 5
    },
    {
      "x": "2019-07-02T12:07:34-04:00",
      "y": 2
    },
    {
      "x": "2019-07-02T12:22:34-04:00",
      "y": 0
    },
    {
      "x": "2019-07-02T12:37:34-04:00",
      "y": 1
    },
    {
      "x": "2019-07-02T12:52:34-04:00",
      "y": 3
    },
    {
      "x": "2019-07-02T13:07:34-04:00",
      "y": 6
    },
    {
      "x": "2019-07-02T13:22:34-04:00",
      "y": 3
    },
    {
      "x": "2019-07-02T13:37:34-04:00",
      "y": 4
    },
    {
      "x": "2019-07-02T13:52:34-04:00",
      "y": 5
    },
    {
      "x": "2019-07-02T14:07:34-04:00",
      "y": 3
    },
    {
      "x": "2019-07-02T14:22:34-04:00",
      "y": 6
    },
    {
      "x": "2019-07-02T14:37:34-04:00",
      "y": 7
    },
    {
      "x": "2019-07-02T14:52:34-04:00",
      "y": 5
    },
    {
      "x": "2019-07-02T15:07:34-04:00",
      "y": 4
    },
    {
      "x": "2019-07-02T15:22:34-04:00",
      "y": 22
    },
    {
      "x": "2019-07-02T15:37:34-04:00",
      "y": 91
    },
    {
      "x": "2019-07-02T15:52:34-04:00",
      "y": 113
    },
    {
      "x": "2019-07-02T16:07:34-04:00",
      "y": 97
    },
    {
      "x": "2019-07-02T16:22:34-04:00",
      "y": 94
    },
    {
      "x": "2019-07-02T16:37:34-04:00",
      "y": 91
    },
    {
      "x": "2019-07-02T16:52:34-04:00",
      "y": 82
    },
    {
      "x": "2019-07-02T17:07:34-04:00",
      "y": 90
    },
    {
      "x": "2019-07-02T17:22:34-04:00",
      "y": 91
    },
    {
      "x": "2019-07-02T17:37:34-04:00",
      "y": 98
    },
    {
      "x": "2019-07-02T17:52:34-04:00",
      "y": 86
    },
    {
      "x": "2019-07-02T18:07:34-04:00",
      "y": 47
    },
    {
      "x": "2019-07-02T18:22:34-04:00",
      "y": 33
    },
    {
      "x": "2019-07-02T18:37:34-04:00",
      "y": 21
    },
    {
      "x": "2019-07-02T18:52:34-04:00",
      "y": 12
    },
    {
      "x": "2019-07-02T19:07:34-04:00",
      "y": 16
    },
    {
      "x": "2019-07-02T19:22:34-04:00",
      "y": 13
    },
    {
      "x": "2019-07-02T19:37:34-04:00",
      "y": 6
    },
    {
      "x": "2019-07-02T19:52:34-04:00",
      "y": 8
    },
    {
      "x": "2019-07-02T20:07:34-04:00",
      "y": 5
    },
    {
      "x": "2019-07-02T20:22:34-04:00",
      "y": 3
    },
    {
      "x": "2019-07-02T20:37:34-04:00",
      "y": 3
    },
    {
      "x": "2019-07-02T20:52:34-04:00",
      "y": 2
    },
    {
      "x": "2019-07-02T21:07:34-04:00",
      "y": 3
    },
    {
      "x": "2019-07-02T21:22:34-04:00",
      "y": 1
    },
    {
      "x": "2019-07-02T21:37:34-04:00",
      "y": 3
    },
    {
      "x": "2019-07-02T21:52:34-04:00",
      "y": 4
    },
    {
      "x": "2019-07-02T22:07:34-04:00",
      "y": 2
    },
    {
      "x": "2019-07-02T22:22:34-04:00",
      "y": 7
    },
    {
      "x": "2019-07-02T22:37:34-04:00",
      "y": 3
    },
    {
      "x": "2019-07-02T22:52:34-04:00",
      "y": 2
    },
    {
      "x": "2019-07-02T23:07:34-04:00",
      "y": 0
    },
    {
      "x": "2019-07-02T23:22:34-04:00",
      "y": 1
    },
    {
      "x": "2019-07-02T23:37:34-04:00",
      "y": 0
    },
    {
      "x": "2019-07-02T23:52:34-04:00",
      "y": 0
    },
    {
      "x": "2019-07-03T00:07:34-04:00",
      "y": 3
    },
    {
      "x": "2019-07-03T00:22:34-04:00",
      "y": 3
    },
    {
      "x": "2019-07-03T00:37:34-04:00",
      "y": 0
    },
    {
      "x": "2019-07-03T00:52:34-04:00",
      "y": 1
    },
    {
      "x": "2019-07-03T01:07:34-04:00",
      "y": 0
    },
    {
      "x": "2019-07-03T01:22:34-04:00",
      "y": 1
    },
    {
      "x": "2019-07-03T01:37:34-04:00",
      "y": 1
    },
    {
      "x": "2019-07-03T01:52:34-04:00",
      "y": 2
    },
    {
      "x": "2019-07-03T02:07:34-04:00",
      "y": 0
    },
    {
      "x": "2019-07-03T02:22:34-04:00",
      "y": 1
    },
    {
      "x": "2019-07-03T02:37:34-04:00",
      "y": 0
    },
    {
      "x": "2019-07-03T02:52:34-04:00",
      "y": 0
    },
    {
      "x": "2019-07-03T03:07:34-04:00",
      "y": 0
    },
    {
      "x": "2019-07-03T03:22:34-04:00",
      "y": 0
    }
  ]
}